tracardi_mongodb_connector/__init__.py
tracardi_mongodb_connector/plugin.py
tracardi_mongodb_connector/model/client.py
tracardi_mongodb_connector/model/configuration.py
tracardi_mongodb_connector/model/__pycache__/client.cpython-38.pyc
tracardi_mongodb_connector/model/__pycache__/configuration.cpython-38.pyc
tracardi_mongodb_connector/test/manual/plugin.py
tracardi_mongodb_connector-0.6.0.dist-info/LICENSE.md
tracardi_mongodb_connector-0.6.0.dist-info/METADATA
tracardi_mongodb_connector-0.6.0.dist-info/WHEEL
tracardi_mongodb_connector-0.6.0.dist-info/top_level.txt
tracardi_mongodb_connector-0.6.0.dist-info/RECORD
